{"v":"5.3.3","fr":29.9700012207031,"ip":0,"op":300.00001221925,"w":335,"h":555,"nm":"strength","ddd":0,"assets":[],"layers":[{"ddd":0,"ind":1,"ty":4,"nm":"strength Outlines","sr":1,"ks":{"o":{"a":1,"k":[{"i":{"x":[0.833],"y":[0.833]},"o":{"x":[0.167],"y":[0.167]},"n":["0p833_0p833_0p167_0p167"],"t":0,"s":[100],"e":[100]},{"t":299.00001217852}],"ix":11},"r":{"a":1,"k":[{"i":{"x":[0.833],"y":[0.833]},"o":{"x":[0.167],"y":[0.167]},"n":["0p833_0p833_0p167_0p167"],"t":0,"s":[0],"e":[-3]},{"i":{"x":[0.833],"y":[0.833]},"o":{"x":[0.167],"y":[0.167]},"n":["0p833_0p833_0p167_0p167"],"t":150,"s":[-3],"e":[0]},{"t":299.00001217852}],"ix":10},"p":{"a":1,"k":[{"i":{"x":0.833,"y":0.833},"o":{"x":0.167,"y":0.167},"n":"0p833_0p833_0p167_0p167","t":0,"s":[167.5,277.5,0],"e":[167.5,277.5,0],"to":[0,0,0],"ti":[0,0,0]},{"t":299.00001217852}],"ix":2},"a":{"a":1,"k":[{"i":{"x":0.833,"y":0.833},"o":{"x":0.167,"y":0.167},"n":"0p833_0p833_0p167_0p167","t":0,"s":[167.5,277.5,0],"e":[167.5,277.5,0],"to":[0,0,0],"ti":[0,0,0]},{"t":299.00001217852}],"ix":1},"s":{"a":1,"k":[{"i":{"x":[0.833,0.833,0.833],"y":[0.833,0.833,0.833]},"o":{"x":[0.167,0.167,0.167],"y":[0.167,0.167,0.167]},"n":["0p833_0p833_0p167_0p167","0p833_0p833_0p167_0p167","0p833_0p833_0p167_0p167"],"t":0,"s":[100,100,100],"e":[91,91,100]},{"i":{"x":[0.833,0.833,0.833],"y":[0.833,0.833,0.833]},"o":{"x":[0.167,0.167,0.167],"y":[0.167,0.167,0.167]},"n":["0p833_0p833_0p167_0p167","0p833_0p833_0p167_0p167","0p833_0p833_0p167_0p167"],"t":150,"s":[91,91,100],"e":[100,100,100]},{"t":299.00001217852}],"ix":6}},"ao":0,"shapes":[{"ty":"gr","it":[{"ind":0,"ty":"sh","ix":1,"ks":{"a":0,"k":{"i":[[-3.836,1.006],[3.73,7.923],[1.552,2.415],[1.676,-3.57],[-8.777,-4.119]],"o":[[-2.021,-8.515],[-1.272,-2.704],[-3.234,1.72],[-4.118,8.777],[3.869,1.817]],"v":[[12.225,15.722],[3.804,-9.088],[-0.465,-16.728],[-8.108,-8.714],[0.325,14.634]],"c":true},"ix":2},"nm":"Path 1","mn":"ADBE Vector Shape - Group","hd":false},{"ty":"fl","c":{"a":0,"k":[0.165000002992,0.325,0.497999991623,1],"ix":4},"o":{"a":0,"k":100,"ix":5},"r":1,"nm":"Fill 1","mn":"ADBE Vector Graphic - Fill","hd":false},{"ty":"tr","p":{"a":0,"k":[236.764,365.761],"ix":2},"a":{"a":0,"k":[0,0],"ix":1},"s":{"a":0,"k":[100,100],"ix":3},"r":{"a":0,"k":0,"ix":6},"o":{"a":0,"k":100,"ix":7},"sk":{"a":0,"k":0,"ix":4},"sa":{"a":0,"k":0,"ix":5},"nm":"Transform"}],"nm":"Group 1","np":4,"cix":2,"ix":1,"mn":"ADBE Vector Group","hd":false},{"ty":"gr","it":[{"ind":0,"ty":"sh","ix":1,"ks":{"a":0,"k":{"i":[[0,0],[0,0],[0,0],[0.643,-0.575],[0,0],[0,0],[0,0],[0,0],[-0.226,-0.477],[0,0]],"o":[[0,0],[0,0],[0,0],[0,0],[0,0],[0,0],[0,0],[0.193,0.499],[0,0],[0,0]],"v":[[-2.683,-6.072],[4.309,-10.218],[1.898,-31.537],[0.8,-30.796],[3.061,-10.804],[-3.931,-6.657],[6.796,9.032],[-8.043,30.071],[-7.417,31.537],[8.043,9.618]],"c":true},"ix":2},"nm":"Path 1","mn":"ADBE Vector Shape - Group","hd":false},{"ty":"fl","c":{"a":0,"k":[0.059000000299,0.630999995213,0.917999985639,1],"ix":4},"o":{"a":0,"k":100,"ix":5},"r":1,"nm":"Fill 1","mn":"ADBE Vector Graphic - Fill","hd":false},{"ty":"tr","p":{"a":0,"k":[162.757,177.882],"ix":2},"a":{"a":0,"k":[0,0],"ix":1},"s":{"a":0,"k":[100,100],"ix":3},"r":{"a":0,"k":0,"ix":6},"o":{"a":0,"k":100,"ix":7},"sk":{"a":0,"k":0,"ix":4},"sa":{"a":0,"k":0,"ix":5},"nm":"Transform"}],"nm":"Group 2","np":4,"cix":2,"ix":2,"mn":"ADBE Vector Group","hd":false},{"ty":"gr","it":[{"ind":0,"ty":"sh","ix":1,"ks":{"a":0,"k":{"i":[[0,0],[1.337,-8.835],[-7.597,-16.108],[0,0],[0,0],[0,0]],"o":[[0,0],[-1.242,8.205],[0,0],[0,0],[0,0],[0,0]],"v":[[5.383,-31.538],[0.325,-21.409],[-3.932,31.538],[11.528,9.617],[0.802,-6.072],[7.794,-10.22]],"c":true},"ix":2},"nm":"Path 1","mn":"ADBE Vector Shape - Group","hd":false},{"ty":"fl","c":{"a":0,"k":[0,0.694000004787,0.922000002394,1],"ix":4},"o":{"a":0,"k":100,"ix":5},"r":1,"nm":"Fill 1","mn":"ADBE Vector Graphic - Fill","hd":false},{"ty":"tr","p":{"a":0,"k":[159.271,177.882],"ix":2},"a":{"a":0,"k":[0,0],"ix":1},"s":{"a":0,"k":[100,100],"ix":3},"r":{"a":0,"k":0,"ix":6},"o":{"a":0,"k":100,"ix":7},"sk":{"a":0,"k":0,"ix":4},"sa":{"a":0,"k":0,"ix":5},"nm":"Transform"}],"nm":"Group 3","np":4,"cix":2,"ix":3,"mn":"ADBE Vector Group","hd":false},{"ty":"gr","it":[{"ind":0,"ty":"sh","ix":1,"ks":{"a":0,"k":{"i":[[0,0],[0,0],[0,0],[0,0],[0,0],[0,0],[0,0],[-0.539,1.891]],"o":[[0,0],[0,0],[0,0],[0,0],[0,0],[0,0],[0,0],[0,0]],"v":[[-7.283,1.445],[8.747,-18.91],[-0.868,-25.234],[-1.805,-24.525],[6.839,-17.727],[-8.747,2.062],[-2.445,25.234],[-1.624,22.256]],"c":true},"ix":2},"nm":"Path 1","mn":"ADBE Vector Shape - Group","hd":false},{"ty":"fl","c":{"a":0,"k":[0.059000000299,0.630999995213,0.917999985639,1],"ix":4},"o":{"a":0,"k":100,"ix":5},"r":1,"nm":"Fill 1","mn":"ADBE Vector Graphic - Fill","hd":false},{"ty":"tr","p":{"a":0,"k":[125.151,187.579],"ix":2},"a":{"a":0,"k":[0,0],"ix":1},"s":{"a":0,"k":[100,100],"ix":3},"r":{"a":0,"k":0,"ix":6},"o":{"a":0,"k":100,"ix":7},"sk":{"a":0,"k":0,"ix":4},"sa":{"a":0,"k":0,"ix":5},"nm":"Transform"}],"nm":"Group 4","np":4,"cix":2,"ix":4,"mn":"ADBE Vector Group","hd":false},{"ty":"gr","it":[{"ind":0,"ty":"sh","ix":1,"ks":{"a":0,"k":{"i":[[0,0],[0,0],[0,0],[0,0],[0,0],[-6.673,16.101],[-0.815,2.975]],"o":[[0,0],[0,0],[0,0],[0,0],[0,0],[5.63,-13.58],[0.592,-2.157]],"v":[[15.58,-34.28],[-9.26,-15.479],[-0.617,-8.68],[-16.202,11.108],[-9.9,34.28],[0.628,3.296],[15.61,-28.161]],"c":true},"ix":2},"nm":"Path 1","mn":"ADBE Vector Shape - Group","hd":false},{"ty":"fl","c":{"a":0,"k":[0,0.694000004787,0.922000002394,1],"ix":4},"o":{"a":0,"k":100,"ix":5},"r":1,"nm":"Fill 1","mn":"ADBE Vector Graphic - Fill","hd":false},{"ty":"tr","p":{"a":0,"k":[132.607,178.533],"ix":2},"a":{"a":0,"k":[0,0],"ix":1},"s":{"a":0,"k":[100,100],"ix":3},"r":{"a":0,"k":0,"ix":6},"o":{"a":0,"k":100,"ix":7},"sk":{"a":0,"k":0,"ix":4},"sa":{"a":0,"k":0,"ix":5},"nm":"Transform"}],"nm":"Group 5","np":4,"cix":2,"ix":5,"mn":"ADBE Vector Group","hd":false},{"ty":"gr","it":[{"ind":0,"ty":"sh","ix":1,"ks":{"a":0,"k":{"i":[[-1.917,9.662],[1.039,9.215],[-1.016,14.815],[-6.372,14.722],[2.123,5.904],[0.011,0.026],[2.501,1.676],[7.302,8.295],[4.625,7.583],[8.869,16.694],[1.379,2.436],[4.245,-1.067],[-1.166,-2.057],[-1.313,-2.471],[-9.851,-16.151],[-5.881,-6.681],[-8.953,-6.002],[-1.094,-2.601],[-0.009,-0.026],[2.323,-5.368],[1.122,-16.36],[-1.651,-14.644],[1.814,-9.142],[8.734,-4.905],[6.397,-0.293],[-9.147,5.137]],"o":[[1.813,-9.143],[-1.651,-14.644],[1.123,-16.359],[2.324,-5.369],[-0.01,-0.026],[-1.094,-2.6],[-8.953,-6.001],[-5.881,-6.681],[-9.852,-16.151],[-1.313,-2.471],[-2.397,-4.23],[1.831,0.673],[1.38,2.435],[8.869,16.694],[4.625,7.582],[7.303,8.295],[2.501,1.676],[0.011,0.026],[2.123,5.905],[-6.372,14.723],[-1.017,14.814],[1.039,9.216],[-1.917,9.662],[-6.855,3.851],[8.216,0.804],[8.733,-4.905]],"v":[[25.63,113.62],[25.973,85.582],[22.048,41.462],[37.82,-3.428],[47.748,-29.116],[47.717,-29.195],[34.361,-38.57],[7.521,-59.267],[-7.889,-81.084],[-34.949,-130.916],[-38.967,-138.289],[-49.871,-142.486],[-45.267,-138.456],[-41.249,-131.084],[-14.189,-81.251],[1.221,-59.435],[28.062,-38.737],[41.417,-29.362],[41.448,-29.284],[31.52,-3.596],[15.749,41.295],[19.673,85.414],[19.33,113.452],[3.537,136.865],[-16.437,142.75],[9.837,137.033]],"c":true},"ix":2},"nm":"Path 1","mn":"ADBE Vector Shape - Group","hd":false},{"ty":"fl","c":{"a":0,"k":[0.059000000299,0.630999995213,0.917999985639,1],"ix":4},"o":{"a":0,"k":100,"ix":5},"r":1,"nm":"Fill 1","mn":"ADBE Vector Graphic - Fill","hd":false},{"ty":"tr","p":{"a":0,"k":[100.469,173.448],"ix":2},"a":{"a":0,"k":[0,0],"ix":1},"s":{"a":0,"k":[100,100],"ix":3},"r":{"a":0,"k":0,"ix":6},"o":{"a":0,"k":100,"ix":7},"sk":{"a":0,"k":0,"ix":4},"sa":{"a":0,"k":0,"ix":5},"nm":"Transform"}],"nm":"Group 6","np":4,"cix":2,"ix":6,"mn":"ADBE Vector Group","hd":false},{"ty":"gr","it":[{"ind":0,"ty":"sh","ix":1,"ks":{"a":0,"k":{"i":[[0.011,0.026],[2.501,1.676],[7.301,8.295],[4.625,7.582],[8.869,16.694],[1.38,2.436],[3.33,-9.997],[-0.725,-1.951],[-2.128,-4.7],[-15.723,-21.126],[5.518,-16.315],[3.83,-8.944],[6.088,-12.388],[16.628,-12.133],[-36.375,20.429],[-1.917,9.662],[1.039,9.215],[-1.017,14.815],[-6.373,14.722],[2.122,5.904]],"o":[[-1.094,-2.6],[-8.953,-6.001],[-5.882,-6.681],[-9.852,-16.152],[-1.312,-2.471],[-5.258,-9.282],[-0.722,2.174],[1.799,4.838],[10.781,23.807],[8.353,11.223],[-3.125,9.239],[-5.434,12.688],[-8.778,17.862],[0,0],[8.733,-4.905],[1.813,-9.143],[-1.651,-14.644],[1.123,-16.359],[2.323,-5.369],[-0.01,-0.026]],"v":[[54.041,-34.141],[40.685,-43.516],[13.845,-64.213],[-1.565,-86.029],[-28.626,-135.862],[-32.644,-143.234],[-55.472,-136.448],[-53.516,-128.639],[-47.463,-114.377],[-11.453,-44.622],[11.707,-4.228],[-0.09,22.483],[-17.426,60.082],[-52.854,113.624],[16.161,132.087],[31.954,108.674],[32.296,80.636],[28.372,36.516],[44.144,-8.374],[54.072,-34.062]],"c":true},"ix":2},"nm":"Path 1","mn":"ADBE Vector Shape - Group","hd":false},{"ty":"fl","c":{"a":0,"k":[0,0.694000004787,0.922000002394,1],"ix":4},"o":{"a":0,"k":100,"ix":5},"r":1,"nm":"Fill 1","mn":"ADBE Vector Graphic - Fill","hd":false},{"ty":"tr","p":{"a":0,"k":[94.146,178.394],"ix":2},"a":{"a":0,"k":[0,0],"ix":1},"s":{"a":0,"k":[100,100],"ix":3},"r":{"a":0,"k":0,"ix":6},"o":{"a":0,"k":100,"ix":7},"sk":{"a":0,"k":0,"ix":4},"sa":{"a":0,"k":0,"ix":5},"nm":"Transform"}],"nm":"Group 7","np":4,"cix":2,"ix":7,"mn":"ADBE Vector Group","hd":false},{"ty":"gr","it":[{"ind":0,"ty":"sh","ix":1,"ks":{"a":0,"k":{"i":[[0,0],[0.396,-9.483],[3.447,-8.842],[-2.317,-9.204],[-4.622,-15.953],[0.853,-2.338],[1.493,-1.406],[14.768,1.483],[1.507,1.107],[0.812,1.444],[1.183,4.645],[0.02,4.465],[-0.64,18.535],[-1.96,6.927],[-11.69,10.192]],"o":[[8.966,3.114],[-0.396,9.483],[-3.448,8.843],[4.055,16.106],[0.691,2.39],[-0.703,1.926],[-10.806,10.173],[-1.861,-0.186],[-1.336,-0.981],[-2.349,-4.178],[-1.102,-4.326],[-0.085,-18.546],[0.248,-7.194],[4.223,-14.922],[0,0]],"v":[[1.447,-72.606],[14.554,-49.507],[6.565,-22.331],[2.599,5.392],[29.528,46.734],[29.717,54.07],[26.075,58.954],[-14.808,72.848],[-20.109,71.234],[-23.107,67.319],[-29.012,54.256],[-30.16,40.948],[-29.69,-14.684],[-27.113,-36.071],[-0.051,-73.096]],"c":false},"ix":2},"nm":"Path 1","mn":"ADBE Vector Shape - Group","hd":false},{"ty":"fl","c":{"a":0,"k":[0.224000010771,0.654999976065,0.596000043084,1],"ix":4},"o":{"a":0,"k":100,"ix":5},"r":1,"nm":"Fill 1","mn":"ADBE Vector Graphic - Fill","hd":false},{"ty":"tr","p":{"a":0,"k":[134.745,211.421],"ix":2},"a":{"a":0,"k":[0,0],"ix":1},"s":{"a":0,"k":[100,100],"ix":3},"r":{"a":0,"k":0,"ix":6},"o":{"a":0,"k":100,"ix":7},"sk":{"a":0,"k":0,"ix":4},"sa":{"a":0,"k":0,"ix":5},"nm":"Transform"}],"nm":"Group 8","np":4,"cix":2,"ix":8,"mn":"ADBE Vector Group","hd":false},{"ty":"gr","it":[{"ind":0,"ty":"sh","ix":1,"ks":{"a":0,"k":{"i":[[1.996,-4.252],[-8.776,-4.119],[-1.842,-0.212],[0.584,5.739],[1.766,5.937]],"o":[[-4.119,8.775],[1.77,0.831],[0.192,-5.808],[-0.465,-4.571],[-4.059,1.576]],"v":[[-4.978,-7.997],[3.454,15.351],[8.905,16.888],[8.46,-0.449],[4.564,-16.888]],"c":true},"ix":2},"nm":"Path 1","mn":"ADBE Vector Shape - Group","hd":false},{"ty":"fl","c":{"a":0,"k":[0.165000002992,0.325,0.497999991623,1],"ix":4},"o":{"a":0,"k":100,"ix":5},"r":1,"nm":"Fill 1","mn":"ADBE Vector Graphic - Fill","hd":false},{"ty":"tr","p":{"a":0,"k":[169.668,393.298],"ix":2},"a":{"a":0,"k":[0,0],"ix":1},"s":{"a":0,"k":[100,100],"ix":3},"r":{"a":0,"k":0,"ix":6},"o":{"a":0,"k":100,"ix":7},"sk":{"a":0,"k":0,"ix":4},"sa":{"a":0,"k":0,"ix":5},"nm":"Transform"}],"nm":"Group 9","np":4,"cix":2,"ix":9,"mn":"ADBE Vector Group","hd":false},{"ty":"gr","it":[{"ind":0,"ty":"sh","ix":1,"ks":{"a":0,"k":{"i":[[3.085,3.314],[0.435,1.391],[6.123,28.794],[2.836,3.301],[8.401,9.2],[3.243,3.497],[4.02,1.502],[3.977,0.956],[-2.578,-3.207],[-3.194,-4.005],[-5.653,-7.146],[-1.589,-7.476],[-8.75,-28.058],[-0.995,-1.071],[-4.664,6.238]],"o":[[-0.995,-1.071],[-8.75,-28.059],[-0.931,-4.379],[-8.11,-9.443],[-3.216,-3.523],[-2.829,-3.05],[-2.557,-0.955],[7.622,8.633],[3.215,3.991],[5.681,7.122],[4.656,5.886],[6.123,28.795],[0.435,1.392],[5.476,5.884],[-4.163,1.792]],"v":[[37.485,68.551],[35.592,64.646],[10.59,-20.007],[4.076,-30.64],[-20.444,-58.779],[-30.129,-69.313],[-40.981,-77.982],[-49.218,-80.981],[-36.688,-66.046],[-27.077,-54.049],[-10.082,-32.642],[2.299,-13.461],[27.301,71.192],[29.194,75.097],[49.218,70.018]],"c":true},"ix":2},"nm":"Path 1","mn":"ADBE Vector Shape - Group","hd":false},{"ty":"fl","c":{"a":0,"k":[0.075,0.211999990426,0.356999984442,1],"ix":4},"o":{"a":0,"k":100,"ix":5},"r":1,"nm":"Fill 1","mn":"ADBE Vector Graphic - Fill","hd":false},{"ty":"tr","p":{"a":0,"k":[210.417,397.653],"ix":2},"a":{"a":0,"k":[0,0],"ix":1},"s":{"a":0,"k":[100,100],"ix":3},"r":{"a":0,"k":0,"ix":6},"o":{"a":0,"k":100,"ix":7},"sk":{"a":0,"k":0,"ix":4},"sa":{"a":0,"k":0,"ix":5},"nm":"Transform"}],"nm":"Group 10","np":4,"cix":2,"ix":10,"mn":"ADBE Vector Group","hd":false},{"ty":"gr","it":[{"ind":0,"ty":"sh","ix":1,"ks":{"a":0,"k":{"i":[[0.24,-0.1],[3.385,1.581],[0.845,9.751],[2.246,27.259],[4.559,8.942],[4.959,10.043],[8.457,17.125],[0,0],[-9.001,-18.227],[-5.087,-9.978],[-0.847,-10.275],[-2.392,-27.582],[-11.284,-5.27],[-3.451,1.431],[-2.363,3.036]],"o":[[-3.451,1.431],[-11.284,-5.27],[-2.392,-27.583],[-0.848,-10.275],[-5.087,-9.978],[-8.456,-17.125],[-6.06,1.976],[9.001,18.227],[4.959,10.043],[4.559,8.942],[2.247,27.259],[0.845,9.751],[3.385,1.581],[3.4,-1.409],[-0.239,0.11]],"v":[[41.461,107.863],[30.575,107.991],[22.002,76.206],[19.898,-6.601],[8.51,-34.88],[-6.884,-64.744],[-32.253,-116.118],[-42.178,-112.881],[-15.175,-58.199],[0.219,-28.334],[11.605,-0.055],[13.711,82.752],[22.284,114.537],[33.169,114.409],[42.178,107.538]],"c":true},"ix":2},"nm":"Path 1","mn":"ADBE Vector Shape - Group","hd":false},{"ty":"fl","c":{"a":0,"k":[0.075,0.211999990426,0.356999984442,1],"ix":4},"o":{"a":0,"k":100,"ix":5},"r":1,"nm":"Fill 1","mn":"ADBE Vector Graphic - Fill","hd":false},{"ty":"tr","p":{"a":0,"k":[130.109,398.136],"ix":2},"a":{"a":0,"k":[0,0],"ix":1},"s":{"a":0,"k":[100,100],"ix":3},"r":{"a":0,"k":0,"ix":6},"o":{"a":0,"k":100,"ix":7},"sk":{"a":0,"k":0,"ix":4},"sa":{"a":0,"k":0,"ix":5},"nm":"Transform"}],"nm":"Group 11","np":4,"cix":2,"ix":11,"mn":"ADBE Vector Group","hd":false},{"ty":"gr","it":[{"ind":0,"ty":"sh","ix":1,"ks":{"a":0,"k":{"i":[[0,0],[-11.309,1.447],[2.61,-1.649],[19.786,6.026],[0,0]],"o":[[0,0],[0,0],[0,0],[-15.313,-4.663],[0,0]],"v":[[-25.792,-10.397],[33.035,4.342],[28.882,10.397],[-3.01,3.087],[-33.036,-8.591]],"c":true},"ix":2},"nm":"Path 1","mn":"ADBE Vector Shape - Group","hd":false},{"ty":"fl","c":{"a":0,"k":[0.023999999551,0.023999999551,0.027000000898,1],"ix":4},"o":{"a":0,"k":100,"ix":5},"r":1,"nm":"Fill 1","mn":"ADBE Vector Graphic - Fill","hd":false},{"ty":"tr","p":{"a":0,"k":[278.408,484.007],"ix":2},"a":{"a":0,"k":[0,0],"ix":1},"s":{"a":0,"k":[100,100],"ix":3},"r":{"a":0,"k":0,"ix":6},"o":{"a":0,"k":100,"ix":7},"sk":{"a":0,"k":0,"ix":4},"sa":{"a":0,"k":0,"ix":5},"nm":"Transform"}],"nm":"Group 12","np":4,"cix":2,"ix":12,"mn":"ADBE Vector Group","hd":false},{"ty":"gr","it":[{"ind":0,"ty":"sh","ix":1,"ks":{"a":0,"k":{"i":[[5.296,3.826],[3.714,19.49],[-14.568,9.503],[-6.845,5.71],[-15.188,12.888],[-0.458,3.935],[1.962,2.616],[3.464,0.287],[1.376,-0.548],[-1.82,-2.428],[0.379,-3.248],[3.02,-2.564],[15.299,-12.76],[7.443,-4.856],[-3.497,-18.356],[-15.693,-11.338],[5.625,-5.286],[3.977,-2.475],[4.848,-2.106],[3.107,-0.638],[-4.309,1.872],[-4.481,2.79],[-3.437,3.229]],"o":[[-15.692,-11.338],[-3.498,-18.355],[7.442,-4.855],[15.3,-12.759],[3.021,-2.563],[0.379,-3.248],[-2.086,-2.78],[-1.479,-0.123],[2.878,0.737],[1.962,2.616],[-0.459,3.936],[-15.189,12.888],[-6.847,5.709],[-14.567,9.503],[3.715,19.49],[5.296,3.827],[-3.437,3.23],[-4.481,2.79],[-2.692,1.17],[4.861,0.156],[4.848,-2.107],[3.977,-2.475],[5.625,-5.286]],"v":[[-7.427,68.133],[-42.311,18.164],[-21.873,-22.128],[-0.652,-37.57],[44.287,-76.951],[51.002,-86.397],[47.77,-95.405],[39.41,-101.092],[35.125,-100.343],[42.197,-94.874],[45.429,-85.867],[38.715,-76.42],[-6.224,-37.039],[-27.447,-21.597],[-47.884,18.695],[-13,68.663],[-10.133,82.991],[-22.345,90.554],[-36.262,98.134],[-45.127,101.059],[-30.689,97.604],[-16.772,90.024],[-4.56,82.461]],"c":true},"ix":2},"nm":"Path 1","mn":"ADBE Vector Shape - Group","hd":false},{"ty":"fl","c":{"a":0,"k":[0.059000000299,0.630999995213,0.917999985639,1],"ix":4},"o":{"a":0,"k":100,"ix":5},"r":1,"nm":"Fill 1","mn":"ADBE Vector Graphic - Fill","hd":false},{"ty":"tr","p":{"a":0,"k":[232.532,182.798],"ix":2},"a":{"a":0,"k":[0,0],"ix":1},"s":{"a":0,"k":[100,100],"ix":3},"r":{"a":0,"k":0,"ix":6},"o":{"a":0,"k":100,"ix":7},"sk":{"a":0,"k":0,"ix":4},"sa":{"a":0,"k":0,"ix":5},"nm":"Transform"}],"nm":"Group 13","np":4,"cix":2,"ix":13,"mn":"ADBE Vector Group","hd":false},{"ty":"gr","it":[{"ind":0,"ty":"sh","ix":1,"ks":{"a":0,"k":{"i":[[0.18,-0.283],[0.253,-1.019],[1.701,-6.827],[-1.333,-9.905],[-3.669,-10.176],[-1.773,-11.948],[-2.334,-3.385],[-7.952,3.455],[-4.481,2.789],[-3.438,3.23],[5.296,3.827],[3.714,19.49],[-14.568,9.504],[-6.846,5.71],[-15.188,12.888],[-0.459,3.935],[1.962,2.616],[3.464,0.286],[2.64,-1.752],[31.609,-10.104],[5.003,-1.108],[0.967,-0.923]],"o":[[-0.554,0.873],[-1.702,6.826],[-2.417,9.697],[1.46,10.851],[4.097,11.363],[0.603,4.065],[5.894,8.546],[4.848,-2.106],[3.977,-2.476],[5.625,-5.286],[-15.693,-11.338],[-3.498,-18.356],[7.442,-4.855],[15.3,-12.76],[3.021,-2.564],[0.378,-3.248],[-2.086,-2.781],[-3.159,-0.262],[-27.648,18.352],[-4.88,1.56],[-1.305,0.288],[-0.246,0.235]],"v":[[-54.939,-36.323],[-56.025,-33.369],[-61.128,-12.889],[-64.647,16.694],[-53.457,47.374],[-44.621,82.455],[-41.152,94.167],[-16.088,96.244],[-2.171,88.665],[10.041,81.101],[7.174,66.773],[-27.71,16.805],[-7.272,-23.488],[13.949,-38.929],[58.888,-78.31],[65.603,-87.757],[62.371,-96.764],[54.01,-102.451],[45.262,-99.232],[-35.758,-42.391],[-50.658,-38.642],[-54.304,-37.104]],"c":true},"ix":2},"nm":"Path 1","mn":"ADBE Vector Shape - Group","hd":false},{"ty":"fl","c":{"a":0,"k":[0,0.670999983245,0.910000011968,1],"ix":4},"o":{"a":0,"k":100,"ix":5},"r":1,"nm":"Fill 1","mn":"ADBE Vector Graphic - Fill","hd":false},{"ty":"tr","p":{"a":0,"k":[217.931,184.158],"ix":2},"a":{"a":0,"k":[0,0],"ix":1},"s":{"a":0,"k":[100,100],"ix":3},"r":{"a":0,"k":0,"ix":6},"o":{"a":0,"k":100,"ix":7},"sk":{"a":0,"k":0,"ix":4},"sa":{"a":0,"k":0,"ix":5},"nm":"Transform"}],"nm":"Group 14","np":4,"cix":2,"ix":14,"mn":"ADBE Vector Group","hd":false},{"ty":"gr","it":[{"ind":0,"ty":"sh","ix":1,"ks":{"a":0,"k":{"i":[[1.008,1.459],[29.88,9.8],[-1.616,15.867],[-12.242,-4.015],[0,0]],"o":[[-10.786,10.762],[-10.38,-3.404],[-3.582,20.089],[37.889,12.427],[-1.153,-1.254]],"v":[[40.547,-20.308],[-28.783,5.068],[-40.202,-26.365],[-30.048,13.938],[43.785,-16.23]],"c":true},"ix":2},"nm":"Path 1","mn":"ADBE Vector Shape - Group","hd":false},{"ty":"fl","c":{"a":0,"k":[0.224000010771,0.654999976065,0.596000043084,1],"ix":4},"o":{"a":0,"k":100,"ix":5},"r":1,"nm":"Fill 1","mn":"ADBE Vector Graphic - Fill","hd":false},{"ty":"tr","p":{"a":0,"k":[139.564,271.529],"ix":2},"a":{"a":0,"k":[0,0],"ix":1},"s":{"a":0,"k":[100,100],"ix":3},"r":{"a":0,"k":0,"ix":6},"o":{"a":0,"k":100,"ix":7},"sk":{"a":0,"k":0,"ix":4},"sa":{"a":0,"k":0,"ix":5},"nm":"Transform"}],"nm":"Group 15","np":4,"cix":2,"ix":15,"mn":"ADBE Vector Group","hd":false},{"ty":"gr","it":[{"ind":0,"ty":"sh","ix":1,"ks":{"a":0,"k":{"i":[[-0.273,-0.146],[-2.246,-0.602],[-2.783,0.467],[-2.296,-0.331],[-25.193,-27.361],[37.89,12.427],[0,0],[-2.614,-0.013],[-1.54,-0.076]],"o":[[1.793,0.963],[3.992,1.07],[2.341,-0.393],[0,0],[0,0],[-37.889,-12.426],[2.614,0.012],[1.542,0.007],[0.407,0.02]],"v":[[22.671,-76.662],[27.97,-73.139],[34.199,-73.465],[41.272,-72.628],[55.86,34.4],[-17.971,64.568],[9.175,-76.978],[17.018,-76.941],[21.66,-76.919]],"c":true},"ix":2},"nm":"Path 1","mn":"ADBE Vector Shape - Group","hd":false},{"ty":"fl","c":{"a":0,"k":[0.298000021542,0.875,0.795999983245,1],"ix":4},"o":{"a":0,"k":100,"ix":5},"r":1,"nm":"Fill 1","mn":"ADBE Vector Graphic - Fill","hd":false},{"ty":"tr","p":{"a":0,"k":[127.488,220.899],"ix":2},"a":{"a":0,"k":[0,0],"ix":1},"s":{"a":0,"k":[100,100],"ix":3},"r":{"a":0,"k":0,"ix":6},"o":{"a":0,"k":100,"ix":7},"sk":{"a":0,"k":0,"ix":4},"sa":{"a":0,"k":0,"ix":5},"nm":"Transform"}],"nm":"Group 16","np":4,"cix":2,"ix":16,"mn":"ADBE Vector Group","hd":false},{"ty":"gr","it":[{"ind":0,"ty":"sh","ix":1,"ks":{"a":0,"k":{"i":[[0,0],[-9,-18.228],[-5.086,-9.978],[-0.846,-10.275],[-2.392,-27.582],[-11.284,-5.27],[-3.451,1.431],[-0.165,7.362],[-0.411,17.403],[1.713,16.831],[1.651,9.158],[3.428,19.018],[-1.227,-1.495],[-5.188,-6.504],[-5.653,-7.146],[-1.59,-7.476],[-8.75,-28.058],[-0.995,-1.071],[-0.776,8.243],[1.594,10.922],[2.562,12.815],[4.657,9.894],[6.622,9.066],[16.622,23.846]],"o":[[9.001,18.228],[4.96,10.043],[4.559,8.942],[2.247,27.259],[0.845,9.751],[3.385,1.581],[6.53,-2.707],[0.387,-17.402],[0.396,-16.87],[-0.944,-9.263],[-3.428,-19.016],[0.309,1.757],[5.277,6.432],[5.68,7.122],[4.656,5.887],[6.123,28.795],[0.434,1.392],[7.14,7.673],[1.032,-10.991],[-1.887,-12.921],[-2.139,-10.702],[-4.884,-10.376],[-17.146,-23.473],[0,0]],"v":[[-87.64,-100.825],[-60.638,-46.142],[-45.243,-16.278],[-33.856,12.001],[-31.751,94.808],[-23.178,126.593],[-12.292,126.465],[0.4,109.958],[1.067,57.743],[2.558,6.77],[-5.904,-26.497],[-14.372,-69.408],[-7.877,-61.921],[7.771,-42.475],[24.764,-21.069],[37.147,-1.888],[62.149,82.765],[64.04,86.67],[86.607,75.737],[80.642,40.521],[74.821,1.782],[64.998,-29.406],[46.131,-56.573],[-3.77,-128.174]],"c":true},"ix":2},"nm":"Path 1","mn":"ADBE Vector Shape - Group","hd":false},{"ty":"fl","c":{"a":0,"k":[0.118000000598,0.270999983245,0.475,1],"ix":4},"o":{"a":0,"k":100,"ix":5},"r":1,"nm":"Fill 1","mn":"ADBE Vector Graphic - Fill","hd":false},{"ty":"tr","p":{"a":0,"k":[175.57,386.079],"ix":2},"a":{"a":0,"k":[0,0],"ix":1},"s":{"a":0,"k":[100,100],"ix":3},"r":{"a":0,"k":0,"ix":6},"o":{"a":0,"k":100,"ix":7},"sk":{"a":0,"k":0,"ix":4},"sa":{"a":0,"k":0,"ix":5},"nm":"Transform"}],"nm":"Group 17","np":4,"cix":2,"ix":17,"mn":"ADBE Vector Group","hd":false},{"ty":"gr","it":[{"ind":0,"ty":"sh","ix":1,"ks":{"a":0,"k":{"i":[[0,0],[-3.588,1.517],[-0.468,-1.092],[0,0]],"o":[[0,0],[1.094,-0.462],[1.521,3.551],[0,0]],"v":[[-5.415,6.22],[1.232,-8.415],[3.894,-5.516],[2.384,8.877]],"c":true},"ix":2},"nm":"Path 1","mn":"ADBE Vector Shape - Group","hd":false},{"ty":"fl","c":{"a":0,"k":[0.952999997606,0.808000033509,0.732999973671,1],"ix":4},"o":{"a":0,"k":100,"ix":5},"r":1,"nm":"Fill 1","mn":"ADBE Vector Graphic - Fill","hd":false},{"ty":"tr","p":{"a":0,"k":[282.386,73.422],"ix":2},"a":{"a":0,"k":[0,0],"ix":1},"s":{"a":0,"k":[100,100],"ix":3},"r":{"a":0,"k":0,"ix":6},"o":{"a":0,"k":100,"ix":7},"sk":{"a":0,"k":0,"ix":4},"sa":{"a":0,"k":0,"ix":5},"nm":"Transform"}],"nm":"Group 18","np":4,"cix":2,"ix":18,"mn":"ADBE Vector Group","hd":false},{"ty":"gr","it":[{"ind":0,"ty":"sh","ix":1,"ks":{"a":0,"k":{"i":[[2.355,2.799],[0,0],[-2.8,2.355],[-2.355,-2.799],[0,0],[2.799,-2.355]],"o":[[0,0],[-2.355,-2.799],[2.799,-2.355],[0,0],[2.354,2.799],[-2.799,2.356]],"v":[[-1.119,9.001],[-9.06,-0.437],[-8.253,-9.809],[1.119,-9.002],[9.061,0.437],[8.253,9.808]],"c":true},"ix":2},"nm":"Path 1","mn":"ADBE Vector Shape - Group","hd":false},{"ty":"fl","c":{"a":0,"k":[0.952999997606,0.808000033509,0.732999973671,1],"ix":4},"o":{"a":0,"k":100,"ix":5},"r":1,"nm":"Fill 1","mn":"ADBE Vector Graphic - Fill","hd":false},{"ty":"tr","p":{"a":0,"k":[299.916,74.556],"ix":2},"a":{"a":0,"k":[0,0],"ix":1},"s":{"a":0,"k":[100,100],"ix":3},"r":{"a":0,"k":0,"ix":6},"o":{"a":0,"k":100,"ix":7},"sk":{"a":0,"k":0,"ix":4},"sa":{"a":0,"k":0,"ix":5},"nm":"Transform"}],"nm":"Group 19","np":4,"cix":2,"ix":19,"mn":"ADBE Vector Group","hd":false},{"ty":"gr","it":[{"ind":0,"ty":"sh","ix":1,"ks":{"a":0,"k":{"i":[[-1.448,0.899],[0,0],[-0.899,-1.448],[0,0],[0,0],[0,0]],"o":[[0,0],[-1.448,0.899],[0,0],[0,0],[0,0],[-0.899,-1.449]],"v":[[0.115,-7.776],[-3.032,-5.823],[-4.026,-1.573],[1.778,7.776],[4.924,5.823],[-0.88,-3.526]],"c":true},"ix":2},"nm":"Path 1","mn":"ADBE Vector Shape - Group","hd":false},{"ty":"fl","c":{"a":0,"k":[0.231000010173,0.270999983245,0.277999997606,1],"ix":4},"o":{"a":0,"k":100,"ix":5},"r":1,"nm":"Fill 1","mn":"ADBE Vector Graphic - Fill","hd":false},{"ty":"tr","p":{"a":0,"k":[291.779,108.412],"ix":2},"a":{"a":0,"k":[0,0],"ix":1},"s":{"a":0,"k":[100,100],"ix":3},"r":{"a":0,"k":0,"ix":6},"o":{"a":0,"k":100,"ix":7},"sk":{"a":0,"k":0,"ix":4},"sa":{"a":0,"k":0,"ix":5},"nm":"Transform"}],"nm":"Group 20","np":4,"cix":2,"ix":20,"mn":"ADBE Vector Group","hd":false},{"ty":"gr","it":[{"ind":0,"ty":"sh","ix":1,"ks":{"a":0,"k":{"i":[[0,0],[0,0],[-0.899,-1.448],[0,0],[0,0],[0,0],[1.447,-0.899],[0,0]],"o":[[0,0],[-1.447,0.898],[0,0],[0,0],[0,0],[-0.899,-1.448],[0,0],[0,0]],"v":[[-9.615,-2.913],[-21.759,4.627],[-22.752,8.876],[-16.948,18.224],[23.651,-6.983],[17.846,-16.331],[13.597,-17.325],[1.453,-9.786]],"c":false},"ix":2},"nm":"Path 1","mn":"ADBE Vector Shape - Group","hd":false},{"ty":"fl","c":{"a":0,"k":[0.310000011968,0.356999984442,0.368999974868,1],"ix":4},"o":{"a":0,"k":100,"ix":5},"r":1,"nm":"Fill 1","mn":"ADBE Vector Graphic - Fill","hd":false},{"ty":"tr","p":{"a":0,"k":[310.505,97.963],"ix":2},"a":{"a":0,"k":[0,0],"ix":1},"s":{"a":0,"k":[100,100],"ix":3},"r":{"a":0,"k":0,"ix":6},"o":{"a":0,"k":100,"ix":7},"sk":{"a":0,"k":0,"ix":4},"sa":{"a":0,"k":0,"ix":5},"nm":"Transform"}],"nm":"Group 21","np":4,"cix":2,"ix":21,"mn":"ADBE Vector Group","hd":false},{"ty":"gr","it":[{"ind":0,"ty":"sh","ix":1,"ks":{"a":0,"k":{"i":[[-2.549,1.583],[0,0],[0,0],[-1.582,-2.548],[0,0],[0,0],[0,0]],"o":[[0,0],[0,0],[-2.548,1.583],[0,0],[0,0],[0,0],[-1.583,-2.548]],"v":[[5.979,-9.434],[2.858,-7.497],[-4.089,-3.184],[-5.837,4.296],[-2.647,9.434],[7.419,3.183],[4.229,-1.955]],"c":true},"ix":2},"nm":"Path 1","mn":"ADBE Vector Shape - Group","hd":false},{"ty":"fl","c":{"a":0,"k":[0.866999966491,0.552999997606,0.097999999102,1],"ix":4},"o":{"a":0,"k":100,"ix":5},"r":1,"nm":"Fill 1","mn":"ADBE Vector Graphic - Fill","hd":false},{"ty":"tr","p":{"a":0,"k":[294.741,94.566],"ix":2},"a":{"a":0,"k":[0,0],"ix":1},"s":{"a":0,"k":[100,100],"ix":3},"r":{"a":0,"k":0,"ix":6},"o":{"a":0,"k":100,"ix":7},"sk":{"a":0,"k":0,"ix":4},"sa":{"a":0,"k":0,"ix":5},"nm":"Transform"}],"nm":"Group 22","np":4,"cix":2,"ix":22,"mn":"ADBE Vector Group","hd":false},{"ty":"gr","it":[{"ind":0,"ty":"sh","ix":1,"ks":{"a":0,"k":{"i":[[-2.041,-3.296],[0,0],[0,0],[0,0],[3.875,-0.093],[10.397,16.747],[0,0],[0,0],[0,0],[-7.627,-2.628]],"o":[[0,0],[0,0],[0,0],[-2.04,-3.296],[-12.345,0.301],[0,0],[0,0],[0,0],[10.398,16.746],[2.396,0.825]],"v":[[25.93,20.705],[28.772,25.288],[27.049,26.357],[24.211,21.772],[14.673,16.547],[-23.39,-10.128],[-28.772,-18.794],[-16.591,-26.357],[-11.21,-17.691],[18.761,14.009]],"c":true},"ix":2},"nm":"Path 1","mn":"ADBE Vector Shape - Group","hd":false},{"ty":"fl","c":{"a":0,"k":[0.866999966491,0.552999997606,0.097999999102,1],"ix":4},"o":{"a":0,"k":100,"ix":5},"r":1,"nm":"Fill 1","mn":"ADBE Vector Graphic - Fill","hd":false},{"ty":"tr","p":{"a":0,"k":[271.58,60.072],"ix":2},"a":{"a":0,"k":[0,0],"ix":1},"s":{"a":0,"k":[100,100],"ix":3},"r":{"a":0,"k":0,"ix":6},"o":{"a":0,"k":100,"ix":7},"sk":{"a":0,"k":0,"ix":4},"sa":{"a":0,"k":0,"ix":5},"nm":"Transform"}],"nm":"Group 23","np":4,"cix":2,"ix":23,"mn":"ADBE Vector Group","hd":false},{"ty":"gr","it":[{"ind":0,"ty":"sh","ix":1,"ks":{"a":0,"k":{"i":[[0,0],[0,0],[-1.803,3.432],[10.397,16.746],[0,0],[0,0],[0,0],[-12.345,0.301],[-2.041,-3.297],[0,0],[0,0]],"o":[[0,0],[-2.05,-3.291],[5.744,-10.931],[0,0],[0,0],[0,0],[10.399,16.747],[3.876,-0.095],[0,0],[0,0],[0,0]],"v":[[29.994,32.194],[27.143,27.618],[26.69,16.751],[19.664,-29.195],[14.283,-37.861],[-32.434,-8.855],[-27.053,-0.189],[11.012,26.486],[20.551,31.711],[23.388,36.296],[29.589,37.861]],"c":true},"ix":2},"nm":"Path 1","mn":"ADBE Vector Shape - Group","hd":false},{"ty":"fl","c":{"a":0,"k":[0.976000019148,0.675,0.187999994615,1],"ix":4},"o":{"a":0,"k":100,"ix":5},"r":1,"nm":"Fill 1","mn":"ADBE Vector Graphic - Fill","hd":false},{"ty":"tr","p":{"a":0,"k":[275.242,50.134],"ix":2},"a":{"a":0,"k":[0,0],"ix":1},"s":{"a":0,"k":[100,100],"ix":3},"r":{"a":0,"k":0,"ix":6},"o":{"a":0,"k":100,"ix":7},"sk":{"a":0,"k":0,"ix":4},"sa":{"a":0,"k":0,"ix":5},"nm":"Transform"}],"nm":"Group 24","np":4,"cix":2,"ix":24,"mn":"ADBE Vector Group","hd":false},{"ty":"gr","it":[{"ind":0,"ty":"sh","ix":1,"ks":{"a":0,"k":{"i":[[-0.598,-4.918],[2.292,-3.54],[0.845,-1.044],[0,0],[0,0],[1.727,-0.199],[4.243,2.782],[-0.046,3.71],[-3.542,2.2],[0,0],[0,0],[0,0],[-2.942,-1.41]],"o":[[0.611,5.036],[-0.946,1.461],[0,0],[0,0],[-1.312,0.294],[-4.187,0.483],[-4.143,-2.717],[0.039,-3.261],[0,0],[0,0],[0,0],[3.543,-2.199],[3.344,1.604]],"v":[[33.691,-16.386],[29.409,-2.534],[26.653,1.254],[-9.729,23.845],[-9.73,23.846],[-14.349,24.635],[-28.663,22.329],[-35.11,12.216],[-29.553,3.749],[-29.413,3.662],[17.295,-25.338],[17.434,-25.426],[27.488,-26.65]],"c":true},"ix":2},"nm":"Path 1","mn":"ADBE Vector Shape - Group","hd":false},{"ind":1,"ty":"sh","ix":2,"ks":{"a":0,"k":{"i":[[5.088,2.441],[5.21,-3.235],[0,0],[0,0],[0,0],[0.064,-5.224],[-5.762,-3.78],[-0.69,0.244],[0,0],[0,0],[0,0],[0,0],[0,0],[1.528,12.567]],"o":[[-4.711,-2.26],[0,0],[0,0],[0,0],[-5.211,3.235],[-0.071,5.645],[10.587,6.943],[0,0],[0,0],[0,0],[0,0],[0,0],[0.523,-0.51],[-0.833,-6.841]],"v":[[29.889,-31.658],[14.504,-30.144],[14.37,-30.059],[-32.347,-1.054],[-32.483,-0.969],[-40.663,12.147],[-31.708,26.975],[-4.121,28.054],[-2.539,27.498],[-2.538,27.497],[26.736,9.32],[26.738,9.319],[27.939,8.148],[39.206,-17.054]],"c":true},"ix":2},"nm":"Path 2","mn":"ADBE Vector Shape - Group","hd":false},{"ty":"mm","mm":1,"nm":"Merge Paths 1","mn":"ADBE Vector Filter - Merge","hd":false},{"ty":"fl","c":{"a":0,"k":[0.866999966491,0.552999997606,0.097999999102,1],"ix":4},"o":{"a":0,"k":100,"ix":5},"r":1,"nm":"Fill 1","mn":"ADBE Vector Graphic - Fill","hd":false},{"ty":"tr","p":{"a":0,"k":[278.095,47.066],"ix":2},"a":{"a":0,"k":[0,0],"ix":1},"s":{"a":0,"k":[100,100],"ix":3},"r":{"a":0,"k":0,"ix":6},"o":{"a":0,"k":100,"ix":7},"sk":{"a":0,"k":0,"ix":4},"sa":{"a":0,"k":0,"ix":5},"nm":"Transform"}],"nm":"Group 25","np":6,"cix":2,"ix":25,"mn":"ADBE Vector Group","hd":false},{"ty":"gr","it":[{"ind":0,"ty":"sh","ix":1,"ks":{"a":0,"k":{"i":[[0,0],[0,0],[-1.582,-2.548],[0,0],[0,0],[0,0],[2.548,-1.582],[0,0]],"o":[[0,0],[-2.548,1.583],[0,0],[0,0],[0,0],[-1.582,-2.548],[0,0],[0,0]],"v":[[-8.002,-2.827],[-14.949,1.486],[-16.698,8.965],[-13.508,14.104],[18.281,-5.635],[15.091,-10.773],[7.612,-12.522],[0.665,-8.209]],"c":true},"ix":2},"nm":"Path 1","mn":"ADBE Vector Shape - Group","hd":false},{"ty":"fl","c":{"a":0,"k":[0.976000019148,0.675,0.187999994615,1],"ix":4},"o":{"a":0,"k":100,"ix":5},"r":1,"nm":"Fill 1","mn":"ADBE Vector Graphic - Fill","hd":false},{"ty":"tr","p":{"a":0,"k":[305.601,89.896],"ix":2},"a":{"a":0,"k":[0,0],"ix":1},"s":{"a":0,"k":[100,100],"ix":3},"r":{"a":0,"k":0,"ix":6},"o":{"a":0,"k":100,"ix":7},"sk":{"a":0,"k":0,"ix":4},"sa":{"a":0,"k":0,"ix":5},"nm":"Transform"}],"nm":"Group 26","np":4,"cix":2,"ix":26,"mn":"ADBE Vector Group","hd":false},{"ty":"gr","it":[{"ind":0,"ty":"sh","ix":1,"ks":{"a":0,"k":{"i":[[0,0],[0,0],[0,0],[0,0]],"o":[[0,0],[0,0],[0,0],[0,0]],"v":[[-20.697,3.123],[2.238,-17.818],[20.697,6.699],[-9.105,17.818]],"c":true},"ix":2},"nm":"Path 1","mn":"ADBE Vector Shape - Group","hd":false},{"ty":"fl","c":{"a":0,"k":[0.952999997606,0.808000033509,0.732999973671,1],"ix":4},"o":{"a":0,"k":100,"ix":5},"r":1,"nm":"Fill 1","mn":"ADBE Vector Graphic - Fill","hd":false},{"ty":"tr","p":{"a":0,"k":[292.639,78.583],"ix":2},"a":{"a":0,"k":[0,0],"ix":1},"s":{"a":0,"k":[100,100],"ix":3},"r":{"a":0,"k":0,"ix":6},"o":{"a":0,"k":100,"ix":7},"sk":{"a":0,"k":0,"ix":4},"sa":{"a":0,"k":0,"ix":5},"nm":"Transform"}],"nm":"Group 27","np":4,"cix":2,"ix":27,"mn":"ADBE Vector Group","hd":false},{"ty":"gr","it":[{"ind":0,"ty":"sh","ix":1,"ks":{"a":0,"k":{"i":[[-1.383,0.963],[2.691,1.394],[-0.801,-1.113],[5.131,2.943],[0.162,-4.1],[-4.473,-2.118],[0.774,-0.422]],"o":[[2.684,-1.875],[-1.125,-0.583],[-7.639,-1.709],[-2.445,3.544],[-0.318,8.05],[1.452,0.687],[0.665,-1.416]],"v":[[11.951,13.468],[7.578,-8.798],[4.766,-0.535],[-11.988,-18.65],[-14.317,-4.902],[-8.873,8.541],[4.673,18.65]],"c":true},"ix":2},"nm":"Path 1","mn":"ADBE Vector Shape - Group","hd":false},{"ty":"fl","c":{"a":0,"k":[0.952999997606,0.808000033509,0.732999973671,1],"ix":4},"o":{"a":0,"k":100,"ix":5},"r":1,"nm":"Fill 1","mn":"ADBE Vector Graphic - Fill","hd":false},{"ty":"tr","p":{"a":0,"k":[39.363,18.65],"ix":2},"a":{"a":0,"k":[0,0],"ix":1},"s":{"a":0,"k":[100,100],"ix":3},"r":{"a":0,"k":0,"ix":6},"o":{"a":0,"k":100,"ix":7},"sk":{"a":0,"k":0,"ix":4},"sa":{"a":0,"k":0,"ix":5},"nm":"Transform"}],"nm":"Group 28","np":4,"cix":2,"ix":28,"mn":"ADBE Vector Group","hd":false},{"ty":"gr","it":[{"ind":0,"ty":"sh","ix":1,"ks":{"a":0,"k":{"i":[[12.323,-7.799],[0,0],[6.778,0.326],[1.159,-2.536],[-1.3,-1.585],[0,0],[-0.38,18.038],[0,0],[-17.498,-7.319]],"o":[[-6.186,3.915],[0,0],[-2.048,-0.099],[-2.223,4.865],[2.728,3.331],[0,0],[0.497,-23.596],[0,0],[8.764,3.666]],"v":[[25.731,0.516],[-3.528,1.654],[-14.274,10.223],[-20.529,13.213],[-16.519,21.6],[-14.211,34.513],[-37.673,6.529],[-17.561,-14.112],[19.863,-27.194]],"c":true},"ix":2},"nm":"Path 1","mn":"ADBE Vector Shape - Group","hd":false},{"ty":"fl","c":{"a":0,"k":[0.125,0.113999998803,0.356999984442,1],"ix":4},"o":{"a":0,"k":100,"ix":5},"r":1,"nm":"Fill 1","mn":"ADBE Vector Graphic - Fill","hd":false},{"ty":"tr","p":{"a":0,"k":[167.077,96.491],"ix":2},"a":{"a":0,"k":[0,0],"ix":1},"s":{"a":0,"k":[100,100],"ix":3},"r":{"a":0,"k":0,"ix":6},"o":{"a":0,"k":100,"ix":7},"sk":{"a":0,"k":0,"ix":4},"sa":{"a":0,"k":0,"ix":5},"nm":"Transform"}],"nm":"Group 29","np":4,"cix":2,"ix":29,"mn":"ADBE Vector Group","hd":false},{"ty":"gr","it":[{"ind":0,"ty":"sh","ix":1,"ks":{"a":0,"k":{"i":[[10.465,2.065],[4.258,-11.273],[0.169,0.034],[0.621,-3.142],[-3.141,-0.62],[-0.131,-0.017],[-1.447,-3.777],[0,0],[0,0],[0,0],[-1.019,-0.201],[-2.874,14.56]],"o":[[-8.977,-1.771],[-0.162,-0.047],[-3.142,-0.62],[-0.62,3.142],[0.133,0.027],[-0.225,4.669],[0,0],[0,0],[0,0],[0.933,0.407],[10.465,2.066],[2.873,-14.559]],"v":[[6.887,-32.068],[-15.577,-15.361],[-16.072,-15.485],[-22.885,-10.919],[-18.318,-4.108],[-17.924,-4.05],[-16.01,8.805],[-20.51,31.613],[-9.232,33.839],[-6.449,19.736],[-3.52,20.657],[20.632,-1.966]],"c":true},"ix":2},"nm":"Path 1","mn":"ADBE Vector Shape - Group","hd":false},{"ty":"fl","c":{"a":0,"k":[0.952999997606,0.808000033509,0.732999973671,1],"ix":4},"o":{"a":0,"k":100,"ix":5},"r":1,"nm":"Fill 1","mn":"ADBE Vector Graphic - Fill","hd":false},{"ty":"tr","p":{"a":0,"k":[168.875,122.199],"ix":2},"a":{"a":0,"k":[0,0],"ix":1},"s":{"a":0,"k":[100,100],"ix":3},"r":{"a":0,"k":0,"ix":6},"o":{"a":0,"k":100,"ix":7},"sk":{"a":0,"k":0,"ix":4},"sa":{"a":0,"k":0,"ix":5},"nm":"Transform"}],"nm":"Group 30","np":4,"cix":2,"ix":30,"mn":"ADBE Vector Group","hd":false},{"ty":"gr","it":[{"ind":0,"ty":"sh","ix":1,"ks":{"a":0,"k":{"i":[[0,0],[6.142,-12.679],[5.292,8.593],[0,0]],"o":[[0,0],[-2.085,4.305],[-9.455,-15.352],[0,0]],"v":[[9.414,-25.357],[11.683,27.766],[-1.816,19.554],[-17.824,-29.524]],"c":true},"ix":2},"nm":"Path 1","mn":"ADBE Vector Shape - Group","hd":false},{"ty":"fl","c":{"a":0,"k":[0.105999995213,0.105999995213,0.136999990426,1],"ix":4},"o":{"a":0,"k":100,"ix":5},"r":1,"nm":"Fill 1","mn":"ADBE Vector Graphic - Fill","hd":false},{"ty":"tr","p":{"a":0,"k":[163.974,524.827],"ix":2},"a":{"a":0,"k":[0,0],"ix":1},"s":{"a":0,"k":[100,100],"ix":3},"r":{"a":0,"k":0,"ix":6},"o":{"a":0,"k":100,"ix":7},"sk":{"a":0,"k":0,"ix":4},"sa":{"a":0,"k":0,"ix":5},"nm":"Transform"}],"nm":"Group 31","np":4,"cix":2,"ix":31,"mn":"ADBE Vector Group","hd":false},{"ty":"gr","it":[{"ind":0,"ty":"sh","ix":1,"ks":{"a":0,"k":{"i":[[0,0],[-5.278,-13.063],[9.922,1.842],[0,0]],"o":[[0,0],[1.791,4.434],[-17.728,-3.293],[0,0]],"v":[[-14.175,-15.327],[34.95,9.849],[16.09,13.484],[-36.741,-4.393]],"c":true},"ix":2},"nm":"Path 1","mn":"ADBE Vector Shape - Group","hd":false},{"ty":"fl","c":{"a":0,"k":[0.105999995213,0.105999995213,0.136999990426,1],"ix":4},"o":{"a":0,"k":100,"ix":5},"r":1,"nm":"Fill 1","mn":"ADBE Vector Graphic - Fill","hd":false},{"ty":"tr","p":{"a":0,"k":[276.352,477.143],"ix":2},"a":{"a":0,"k":[0,0],"ix":1},"s":{"a":0,"k":[100,100],"ix":3},"r":{"a":0,"k":0,"ix":6},"o":{"a":0,"k":100,"ix":7},"sk":{"a":0,"k":0,"ix":4},"sa":{"a":0,"k":0,"ix":5},"nm":"Transform"}],"nm":"Group 32","np":4,"cix":2,"ix":32,"mn":"ADBE Vector Group","hd":false},{"ty":"gr","it":[{"ind":0,"ty":"sh","ix":1,"ks":{"a":0,"k":{"i":[[3.127,0],[0,-3.127],[-3.127,0],[0,3.128]],"o":[[-3.127,0],[0,3.128],[3.127,0],[0,-3.127]],"v":[[0,-5.672],[-5.671,0],[0,5.671],[5.671,0]],"c":true},"ix":2},"nm":"Path 1","mn":"ADBE Vector Shape - Group","hd":false},{"ind":1,"ty":"sh","ix":2,"ks":{"a":0,"k":{"i":[[4.601,0],[0,4.6],[-4.601,0],[0,-4.601]],"o":[[-4.601,0],[0,-4.601],[4.601,0],[0,4.6]],"v":[[0,8.344],[-8.343,0],[0,-8.344],[8.343,0]],"c":true},"ix":2},"nm":"Path 2","mn":"ADBE Vector Shape - Group","hd":false},{"ty":"mm","mm":1,"nm":"Merge Paths 1","mn":"ADBE Vector Filter - Merge","hd":false},{"ty":"fl","c":{"a":0,"k":[0.419999994016,0.969000004787,0.745000023935,1],"ix":4},"o":{"a":0,"k":100,"ix":5},"r":1,"nm":"Fill 1","mn":"ADBE Vector Graphic - Fill","hd":false},{"ty":"tr","p":{"a":0,"k":[13.28,248.522],"ix":2},"a":{"a":0,"k":[0,0],"ix":1},"s":{"a":0,"k":[100,100],"ix":3},"r":{"a":0,"k":0,"ix":6},"o":{"a":0,"k":100,"ix":7},"sk":{"a":0,"k":0,"ix":4},"sa":{"a":0,"k":0,"ix":5},"nm":"Transform"}],"nm":"Group 33","np":6,"cix":2,"ix":33,"mn":"ADBE Vector Group","hd":false},{"ty":"gr","it":[{"ind":0,"ty":"sh","ix":1,"ks":{"a":0,"k":{"i":[[11.445,0],[0,-11.445],[-11.445,0],[0,11.445]],"o":[[-11.445,0],[0,11.445],[11.445,0],[0,-11.445]],"v":[[0,-20.757],[-20.757,0],[0,20.757],[20.755,0]],"c":true},"ix":2},"nm":"Path 1","mn":"ADBE Vector Shape - Group","hd":false},{"ind":1,"ty":"sh","ix":2,"ks":{"a":0,"k":{"i":[[16.838,0],[0,16.839],[-16.838,0],[0,-16.839]],"o":[[-16.838,0],[0,-16.839],[16.838,0],[0,16.839]],"v":[[0,30.538],[-30.537,0],[0,-30.538],[30.538,0]],"c":true},"ix":2},"nm":"Path 2","mn":"ADBE Vector Shape - Group","hd":false},{"ty":"mm","mm":1,"nm":"Merge Paths 1","mn":"ADBE Vector Filter - Merge","hd":false},{"ty":"fl","c":{"a":0,"k":[0.419999994016,0.969000004787,0.745000023935,1],"ix":4},"o":{"a":0,"k":100,"ix":5},"r":1,"nm":"Fill 1","mn":"ADBE Vector Graphic - Fill","hd":false},{"ty":"tr","p":{"a":0,"k":[264.207,303.497],"ix":2},"a":{"a":0,"k":[0,0],"ix":1},"s":{"a":0,"k":[100,100],"ix":3},"r":{"a":0,"k":0,"ix":6},"o":{"a":0,"k":100,"ix":7},"sk":{"a":0,"k":0,"ix":4},"sa":{"a":0,"k":0,"ix":5},"nm":"Transform"}],"nm":"Group 34","np":6,"cix":2,"ix":34,"mn":"ADBE Vector Group","hd":false}],"ip":0,"op":300.00001221925,"st":0,"bm":0}],"markers":[]}